{
	"id": "0RjcyqsUgsNQnPO",
	"json": "{\"id\":\"0RjcyqsUgsNQnPO\",\"url\":\"https://www.cde.ca.gov/sp/sw/t1/essaassistdatafiles.asp\",\"loadedUrl\":\"https://www.cde.ca.gov/sp/sw/t1/essaassistdatafiles.asp\",\"uniqueKey\":\"https://www.cde.ca.gov/sp/sw/t1/essaassistdatafiles.asp\",\"method\":\"GET\",\"noRetry\":false,\"retryCount\":0,\"errorMessages\":[],\"headers\":{},\"userData\":{\"__crawlee\":{\"crawlDepth\":3,\"enqueueStrategy\":\"same-domain\",\"state\":4}},\"handledAt\":\"2026-06-01T23:32:03.584Z\"}",
	"method": "GET",
	"orderNo": null,
	"retryCount": 0,
	"uniqueKey": "https://www.cde.ca.gov/sp/sw/t1/essaassistdatafiles.asp",
	"url": "https://www.cde.ca.gov/sp/sw/t1/essaassistdatafiles.asp"
}