{
	"id": "6t9kQhChNdliyhB",
	"json": "{\"id\":\"6t9kQhChNdliyhB\",\"url\":\"https://www.chhs.ca.gov/care-act/a-structured-pathway/\",\"loadedUrl\":\"https://www.chhs.ca.gov/care-act/a-structured-pathway/\",\"uniqueKey\":\"https://www.chhs.ca.gov/care-act/a-structured-pathway\",\"method\":\"GET\",\"noRetry\":false,\"retryCount\":0,\"errorMessages\":[],\"headers\":{},\"userData\":{\"__crawlee\":{\"crawlDepth\":3,\"enqueueStrategy\":\"same-domain\",\"state\":4}},\"handledAt\":\"2026-06-01T23:30:55.273Z\"}",
	"method": "GET",
	"orderNo": null,
	"retryCount": 0,
	"uniqueKey": "https://www.chhs.ca.gov/care-act/a-structured-pathway",
	"url": "https://www.chhs.ca.gov/care-act/a-structured-pathway/"
}