{
	"id": "7ADLE3C7DHcmPJa",
	"json": "{\"id\":\"7ADLE3C7DHcmPJa\",\"url\":\"https://give.ucdavis.edu/ATXC\",\"loadedUrl\":\"https://give.ucdavis.edu/ATXC\",\"uniqueKey\":\"https://give.ucdavis.edu/ATXC\",\"method\":\"GET\",\"noRetry\":false,\"retryCount\":0,\"errorMessages\":[],\"headers\":{},\"userData\":{\"__crawlee\":{\"crawlDepth\":3,\"enqueueStrategy\":\"same-domain\",\"state\":4}},\"handledAt\":\"2026-06-01T23:25:54.904Z\"}",
	"method": "GET",
	"orderNo": null,
	"retryCount": 0,
	"uniqueKey": "https://give.ucdavis.edu/ATXC",
	"url": "https://give.ucdavis.edu/ATXC"
}