{
	"id": "7TxEM66MI7H20U0",
	"json": "{\"id\":\"7TxEM66MI7H20U0\",\"url\":\"https://sitefarm.ucdavis.edu/sign-up/other-web-resources\",\"loadedUrl\":\"https://sitefarm.ucdavis.edu/sign-up/other-web-resources\",\"uniqueKey\":\"https://sitefarm.ucdavis.edu/sign-up/other-web-resources\",\"method\":\"GET\",\"noRetry\":false,\"retryCount\":0,\"errorMessages\":[],\"headers\":{},\"userData\":{\"__crawlee\":{\"crawlDepth\":3,\"enqueueStrategy\":\"same-domain\",\"state\":4}},\"handledAt\":\"2026-06-01T23:02:48.509Z\"}",
	"method": "GET",
	"orderNo": null,
	"retryCount": 0,
	"uniqueKey": "https://sitefarm.ucdavis.edu/sign-up/other-web-resources",
	"url": "https://sitefarm.ucdavis.edu/sign-up/other-web-resources"
}