{
	"id": "8ewEQDORVg6S7zE",
	"json": "{\"id\":\"8ewEQDORVg6S7zE\",\"url\":\"https://recruit.ucdavis.edu/JPF07487\",\"loadedUrl\":\"https://recruit.ucdavis.edu/JPF07487\",\"uniqueKey\":\"https://recruit.ucdavis.edu/JPF07487\",\"method\":\"GET\",\"noRetry\":false,\"retryCount\":0,\"errorMessages\":[],\"headers\":{},\"userData\":{\"__crawlee\":{\"crawlDepth\":3,\"enqueueStrategy\":\"same-domain\",\"state\":4}},\"handledAt\":\"2026-06-01T15:33:25.365Z\"}",
	"method": "GET",
	"orderNo": null,
	"retryCount": 0,
	"uniqueKey": "https://recruit.ucdavis.edu/JPF07487",
	"url": "https://recruit.ucdavis.edu/JPF07487"
}