{
	"id": "8v1EaVCM3JcWctY",
	"json": "{\"id\":\"8v1EaVCM3JcWctY\",\"url\":\"https://www.cde.ca.gov/ls/yd/rs/\",\"loadedUrl\":\"https://www.cde.ca.gov/ls/yd/rs/\",\"uniqueKey\":\"https://www.cde.ca.gov/ls/yd/rs\",\"method\":\"GET\",\"noRetry\":false,\"retryCount\":0,\"errorMessages\":[],\"headers\":{},\"userData\":{\"__crawlee\":{\"crawlDepth\":2,\"enqueueStrategy\":\"same-domain\",\"state\":4}},\"handledAt\":\"2026-06-01T15:26:35.699Z\"}",
	"method": "GET",
	"orderNo": null,
	"retryCount": 0,
	"uniqueKey": "https://www.cde.ca.gov/ls/yd/rs",
	"url": "https://www.cde.ca.gov/ls/yd/rs/"
}