{
	"id": "cbB8d4EX0FN7n09",
	"json": "{\"id\":\"cbB8d4EX0FN7n09\",\"url\":\"https://www.cdph.ca.gov/Pages/allDiseases.aspx\",\"loadedUrl\":\"https://www.cdph.ca.gov/Pages/allDiseases.aspx\",\"uniqueKey\":\"https://www.cdph.ca.gov/Pages/allDiseases.aspx\",\"method\":\"GET\",\"noRetry\":false,\"retryCount\":0,\"errorMessages\":[],\"headers\":{},\"userData\":{\"__crawlee\":{\"crawlDepth\":1,\"enqueueStrategy\":\"same-domain\",\"state\":4}},\"handledAt\":\"2026-06-01T14:59:38.266Z\"}",
	"method": "GET",
	"orderNo": null,
	"retryCount": 0,
	"uniqueKey": "https://www.cdph.ca.gov/Pages/allDiseases.aspx",
	"url": "https://www.cdph.ca.gov/Pages/allDiseases.aspx"
}