{
	"id": "Fg9ASdWbi5wAI6Z",
	"json": "{\"id\":\"Fg9ASdWbi5wAI6Z\",\"url\":\"https://oag.ca.gov/\",\"loadedUrl\":\"https://oag.ca.gov/\",\"uniqueKey\":\"https://oag.ca.gov\",\"method\":\"GET\",\"noRetry\":false,\"retryCount\":0,\"errorMessages\":[],\"headers\":{},\"userData\":{\"__crawlee\":{\"crawlDepth\":3,\"enqueueStrategy\":\"same-domain\",\"state\":4}},\"handledAt\":\"2026-06-01T23:07:46.736Z\"}",
	"method": "GET",
	"orderNo": null,
	"retryCount": 0,
	"uniqueKey": "https://oag.ca.gov",
	"url": "https://oag.ca.gov/"
}