{
	"id": "FGmUSXvJICcgfSL",
	"json": "{\"id\":\"FGmUSXvJICcgfSL\",\"url\":\"https://www.cdph.ca.gov/Programs/CHCQ/LCP/Pages/AFL-26-16.aspx\",\"loadedUrl\":\"https://www.cdph.ca.gov/Programs/CHCQ/LCP/Pages/AFL-26-16.aspx\",\"uniqueKey\":\"https://www.cdph.ca.gov/Programs/CHCQ/LCP/Pages/AFL-26-16.aspx\",\"method\":\"GET\",\"noRetry\":false,\"retryCount\":0,\"errorMessages\":[],\"headers\":{},\"userData\":{\"__crawlee\":{\"crawlDepth\":2,\"enqueueStrategy\":\"same-domain\",\"state\":4}},\"handledAt\":\"2026-06-01T20:29:47.148Z\"}",
	"method": "GET",
	"orderNo": null,
	"retryCount": 0,
	"uniqueKey": "https://www.cdph.ca.gov/Programs/CHCQ/LCP/Pages/AFL-26-16.aspx",
	"url": "https://www.cdph.ca.gov/Programs/CHCQ/LCP/Pages/AFL-26-16.aspx"
}