{
	"id": "FZFhNOZMpuZvGPb",
	"json": "{\"id\":\"FZFhNOZMpuZvGPb\",\"url\":\"https://www.library.ca.gov/law/\",\"loadedUrl\":\"https://www.library.ca.gov/law/\",\"uniqueKey\":\"https://www.library.ca.gov/law\",\"method\":\"GET\",\"noRetry\":false,\"retryCount\":0,\"errorMessages\":[],\"headers\":{},\"userData\":{\"__crawlee\":{\"crawlDepth\":3,\"enqueueStrategy\":\"same-domain\",\"state\":4}},\"handledAt\":\"2026-06-01T15:39:17.607Z\"}",
	"method": "GET",
	"orderNo": null,
	"retryCount": 0,
	"uniqueKey": "https://www.library.ca.gov/law",
	"url": "https://www.library.ca.gov/law/"
}