{
	"id": "Js0zOT3ZJQb9xVA",
	"json": "{\"id\":\"Js0zOT3ZJQb9xVA\",\"url\":\"https://cnprc.ucdavis.edu/infectious-disease\",\"loadedUrl\":\"https://cnprc.ucdavis.edu/infectious-disease\",\"uniqueKey\":\"https://cnprc.ucdavis.edu/infectious-disease\",\"method\":\"GET\",\"noRetry\":false,\"retryCount\":0,\"errorMessages\":[],\"headers\":{},\"userData\":{\"__crawlee\":{\"crawlDepth\":3,\"enqueueStrategy\":\"same-domain\",\"state\":4}},\"handledAt\":\"2026-06-01T23:25:12.626Z\"}",
	"method": "GET",
	"orderNo": null,
	"retryCount": 0,
	"uniqueKey": "https://cnprc.ucdavis.edu/infectious-disease",
	"url": "https://cnprc.ucdavis.edu/infectious-disease"
}