{
	"id": "l8J02s0suoMjdJe",
	"json": "{\"id\":\"l8J02s0suoMjdJe\",\"url\":\"https://rarediseases.org/rare-diseases/haim-munk-syndrome/\",\"loadedUrl\":\"https://rarediseases.org/rare-diseases/haim-munk-syndrome/\",\"uniqueKey\":\"https://rarediseases.org/rare-diseases/haim-munk-syndrome\",\"method\":\"GET\",\"noRetry\":false,\"retryCount\":0,\"errorMessages\":[],\"headers\":{},\"userData\":{\"__crawlee\":{\"crawlDepth\":3,\"enqueueStrategy\":\"same-domain\",\"state\":4}},\"handledAt\":\"2026-06-01T23:10:01.992Z\"}",
	"method": "GET",
	"orderNo": null,
	"retryCount": 0,
	"uniqueKey": "https://rarediseases.org/rare-diseases/haim-munk-syndrome",
	"url": "https://rarediseases.org/rare-diseases/haim-munk-syndrome/"
}