{
	"id": "PEmHEspdd2lyQLn",
	"json": "{\"id\":\"PEmHEspdd2lyQLn\",\"url\":\"https://www.parks.ca.gov/?page_id=466\",\"loadedUrl\":\"https://www.parks.ca.gov/?page_id=466\",\"uniqueKey\":\"https://www.parks.ca.gov?page_id=466\",\"method\":\"GET\",\"noRetry\":false,\"retryCount\":0,\"errorMessages\":[],\"headers\":{},\"userData\":{\"__crawlee\":{\"crawlDepth\":3,\"enqueueStrategy\":\"same-domain\",\"state\":4}},\"handledAt\":\"2026-06-01T15:35:48.649Z\"}",
	"method": "GET",
	"orderNo": null,
	"retryCount": 0,
	"uniqueKey": "https://www.parks.ca.gov?page_id=466",
	"url": "https://www.parks.ca.gov/?page_id=466"
}