{
	"id": "qoLMCvoWZgMzhV1",
	"json": "{\"id\":\"qoLMCvoWZgMzhV1\",\"url\":\"https://rarediseases.org/driving-policy/nord-state-report-card/\",\"loadedUrl\":\"https://rarediseases.org/driving-policy/nord-state-report-card/\",\"uniqueKey\":\"https://rarediseases.org/driving-policy/nord-state-report-card\",\"method\":\"GET\",\"noRetry\":false,\"retryCount\":0,\"errorMessages\":[],\"headers\":{},\"userData\":{\"__crawlee\":{\"crawlDepth\":1,\"enqueueStrategy\":\"same-domain\",\"state\":4}},\"handledAt\":\"2026-06-01T14:57:05.226Z\"}",
	"method": "GET",
	"orderNo": null,
	"retryCount": 0,
	"uniqueKey": "https://rarediseases.org/driving-policy/nord-state-report-card",
	"url": "https://rarediseases.org/driving-policy/nord-state-report-card/"
}