{
	"id": "RaNAYlhPDouOkrV",
	"json": "{\"id\":\"RaNAYlhPDouOkrV\",\"url\":\"https://health.ucdavis.edu/medalumni/calendar/index.html\",\"loadedUrl\":\"https://health.ucdavis.edu/medalumni/calendar/index.html\",\"uniqueKey\":\"https://health.ucdavis.edu/medalumni/calendar/index.html\",\"method\":\"GET\",\"noRetry\":false,\"retryCount\":0,\"errorMessages\":[],\"headers\":{},\"userData\":{\"__crawlee\":{\"crawlDepth\":3,\"enqueueStrategy\":\"same-domain\",\"state\":4}},\"handledAt\":\"2026-06-01T23:32:07.144Z\"}",
	"method": "GET",
	"orderNo": null,
	"retryCount": 0,
	"uniqueKey": "https://health.ucdavis.edu/medalumni/calendar/index.html",
	"url": "https://health.ucdavis.edu/medalumni/calendar/index.html"
}