{
	"id": "SbMe4ndoyTuP4eR",
	"json": "{\"id\":\"SbMe4ndoyTuP4eR\",\"url\":\"https://mindbrain.sf.ucdavis.edu/directions-uc-davis-campus-bus\",\"loadedUrl\":\"https://mindbrain.sf.ucdavis.edu/directions-uc-davis-campus-bus\",\"uniqueKey\":\"https://mindbrain.sf.ucdavis.edu/directions-uc-davis-campus-bus\",\"method\":\"GET\",\"noRetry\":false,\"retryCount\":0,\"errorMessages\":[],\"headers\":{},\"userData\":{\"__crawlee\":{\"crawlDepth\":3,\"enqueueStrategy\":\"same-domain\",\"state\":4}},\"handledAt\":\"2026-06-01T23:27:18.194Z\"}",
	"method": "GET",
	"orderNo": null,
	"retryCount": 0,
	"uniqueKey": "https://mindbrain.sf.ucdavis.edu/directions-uc-davis-campus-bus",
	"url": "https://mindbrain.sf.ucdavis.edu/directions-uc-davis-campus-bus"
}