{
	"id": "szqBiiLMo058yjd",
	"json": "{\"id\":\"szqBiiLMo058yjd\",\"url\":\"https://genomecenter.ucdavis.edu/membership\",\"loadedUrl\":\"https://genomecenter.ucdavis.edu/membership\",\"uniqueKey\":\"https://genomecenter.ucdavis.edu/membership\",\"method\":\"GET\",\"noRetry\":false,\"retryCount\":0,\"errorMessages\":[],\"headers\":{},\"userData\":{\"__crawlee\":{\"crawlDepth\":3,\"enqueueStrategy\":\"same-domain\",\"state\":4}},\"handledAt\":\"2026-06-01T23:25:09.559Z\"}",
	"method": "GET",
	"orderNo": null,
	"retryCount": 0,
	"uniqueKey": "https://genomecenter.ucdavis.edu/membership",
	"url": "https://genomecenter.ucdavis.edu/membership"
}