{
	"id": "sZxLLU52v275EBX",
	"json": "{\"id\":\"sZxLLU52v275EBX\",\"url\":\"https://profiles.ucdavis.edu/lori.madden\",\"loadedUrl\":\"https://profiles.ucdavis.edu/lori.madden\",\"uniqueKey\":\"https://profiles.ucdavis.edu/lori.madden\",\"method\":\"GET\",\"noRetry\":false,\"retryCount\":0,\"errorMessages\":[],\"headers\":{},\"userData\":{\"__crawlee\":{\"crawlDepth\":3,\"enqueueStrategy\":\"same-domain\",\"state\":4}},\"handledAt\":\"2026-06-01T23:32:26.765Z\"}",
	"method": "GET",
	"orderNo": null,
	"retryCount": 0,
	"uniqueKey": "https://profiles.ucdavis.edu/lori.madden",
	"url": "https://profiles.ucdavis.edu/lori.madden"
}