{
	"id": "uMhSU3lYYHty1Cu",
	"json": "{\"id\":\"uMhSU3lYYHty1Cu\",\"url\":\"https://www.cdss.ca.gov/inforesources/ihss/evv\",\"loadedUrl\":\"https://www.cdss.ca.gov/inforesources/ihss/evv\",\"uniqueKey\":\"https://www.cdss.ca.gov/inforesources/ihss/evv\",\"method\":\"GET\",\"noRetry\":false,\"retryCount\":0,\"errorMessages\":[],\"headers\":{},\"userData\":{\"__crawlee\":{\"crawlDepth\":2,\"enqueueStrategy\":\"same-domain\",\"state\":4}},\"handledAt\":\"2026-06-01T15:10:03.468Z\"}",
	"method": "GET",
	"orderNo": null,
	"retryCount": 0,
	"uniqueKey": "https://www.cdss.ca.gov/inforesources/ihss/evv",
	"url": "https://www.cdss.ca.gov/inforesources/ihss/evv"
}