{
	"id": "YCNBQfrEmDEgIKf",
	"json": "{\"id\":\"YCNBQfrEmDEgIKf\",\"url\":\"https://www.csb-cde.ca.gov/about/events/whitecaneday.aspx\",\"loadedUrl\":\"https://www.csb-cde.ca.gov/about/events/whitecaneday.aspx\",\"uniqueKey\":\"https://www.csb-cde.ca.gov/about/events/whitecaneday.aspx\",\"method\":\"GET\",\"noRetry\":false,\"retryCount\":0,\"errorMessages\":[],\"headers\":{},\"userData\":{\"__crawlee\":{\"crawlDepth\":1,\"enqueueStrategy\":\"same-domain\",\"state\":4}},\"handledAt\":\"2026-06-01T14:58:26.159Z\"}",
	"method": "GET",
	"orderNo": null,
	"retryCount": 0,
	"uniqueKey": "https://www.csb-cde.ca.gov/about/events/whitecaneday.aspx",
	"url": "https://www.csb-cde.ca.gov/about/events/whitecaneday.aspx"
}