{
	"id": "YlmIRRXnZuNs5mv",
	"json": "{\"id\":\"YlmIRRXnZuNs5mv\",\"url\":\"https://give.ucdavis.edu/GSM1/324818\",\"loadedUrl\":\"https://give.ucdavis.edu/GSM1/324818\",\"uniqueKey\":\"https://give.ucdavis.edu/GSM1/324818\",\"method\":\"GET\",\"noRetry\":false,\"retryCount\":0,\"errorMessages\":[],\"headers\":{},\"userData\":{\"__crawlee\":{\"crawlDepth\":3,\"enqueueStrategy\":\"same-domain\",\"state\":4}},\"handledAt\":\"2026-06-01T23:25:54.329Z\"}",
	"method": "GET",
	"orderNo": null,
	"retryCount": 0,
	"uniqueKey": "https://give.ucdavis.edu/GSM1/324818",
	"url": "https://give.ucdavis.edu/GSM1/324818"
}