{
	"id": "YRUtlVb9zXA5imf",
	"json": "{\"id\":\"YRUtlVb9zXA5imf\",\"url\":\"http://cdss.ca.gov/inforesources/immigration\",\"loadedUrl\":\"https://cdss.ca.gov/inforesources/immigration\",\"uniqueKey\":\"http://cdss.ca.gov/inforesources/immigration\",\"method\":\"GET\",\"noRetry\":false,\"retryCount\":0,\"errorMessages\":[],\"headers\":{},\"userData\":{\"__crawlee\":{\"crawlDepth\":3,\"enqueueStrategy\":\"same-domain\",\"state\":4}},\"handledAt\":\"2026-06-01T22:59:01.849Z\"}",
	"method": "GET",
	"orderNo": null,
	"retryCount": 0,
	"uniqueKey": "http://cdss.ca.gov/inforesources/immigration",
	"url": "http://cdss.ca.gov/inforesources/immigration"
}